superodejqb/__init__.py
superodejqb/core.py
supercodejqb-3.1.0.dist-info/METADATA
supercodejqb-3.1.0.dist-info/WHEEL
supercodejqb-3.1.0.dist-info/entry_points.txt
supercodejqb-3.1.0.dist-info/top_level.txt
supercodejqb-3.1.0.dist-info/RECORD
